poetry_test/__init__.py
poetry_issue_test-0.1.6.dist-info/LICENSE
poetry_issue_test-0.1.6.dist-info/METADATA
poetry_issue_test-0.1.6.dist-info/WHEEL
poetry_issue_test-0.1.6.dist-info/RECORD
