Metadata-Version: 2.1
Name: poetry-issue-test
Version: 0.1.6
Summary: 
Requires-Python: >=3.11,<4.0
Classifier: Programming Language :: Python :: 3
Classifier: Programming Language :: Python :: 3.11
Provides-Extra: http
Provides-Extra: postgres
Requires-Dist: httpx (>=0.24.1,<0.25.0) ; extra == "http"
Requires-Dist: ibis-framework[duckdb] (>=5.1.0,<6.0.0) ; extra == "postgres"
Requires-Dist: ibis-framework[postgres] (>=5.1.0,<6.0.0) ; extra == "postgres"
Requires-Dist: requests (>=2.31.0,<3.0.0)
